scripts/create_demo_db.py
scripts/create_dummy_users.py
scripts/import_csv.py
static/favicon.ico
zen_auth/server/ENV.py
zen_auth/server/__init__.py
zen_auth/server/_version.py
zen_auth/server/claims_self.py
zen_auth/server/config.py
zen_auth/server/lifespan.py
zen_auth/server/middleware.py
zen_auth/server/run.py
zen_auth/server/api/__init__.py
zen_auth/server/api/util/__init__.py
zen_auth/server/api/util/error_redirect.py
zen_auth/server/api/util/req_id.py
zen_auth/server/api/util/router_factory.py
zen_auth/server/api/v1/__init__.py
zen_auth/server/api/v1/_assets.py
zen_auth/server/api/v1/_tmp_lib.py
zen_auth/server/api/v1/helper.js
zen_auth/server/api/v1/ui_ids.py
zen_auth/server/api/v1/url_names.py
zen_auth/server/api/v1/admin/__init__.py
zen_auth/server/api/v1/admin/admin.py
zen_auth/server/api/v1/admin/client_app.py
zen_auth/server/api/v1/admin/client_app_tmpl.py
zen_auth/server/api/v1/admin/dual_list.js
zen_auth/server/api/v1/admin/role.py
zen_auth/server/api/v1/admin/role_tmpl.py
zen_auth/server/api/v1/admin/scope.py
zen_auth/server/api/v1/admin/scope_tmpl.py
zen_auth/server/api/v1/admin/user.py
zen_auth/server/api/v1/admin/user_tmpl.py
zen_auth/server/api/v1/admin/zenauth_admin.css
zen_auth/server/api/v1/auth/__init__.py
zen_auth/server/api/v1/auth/auth.py
zen_auth/server/api/v1/auth/auth_tmpl.py
zen_auth/server/api/v1/meta/__init__.py
zen_auth/server/api/v1/meta/meta.py
zen_auth/server/api/v1/verify/__init__.py
zen_auth/server/api/v1/verify/verify.py
zen_auth/server/persistence/__init__.py
zen_auth/server/persistence/base.py
zen_auth/server/persistence/init_db.py
zen_auth/server/persistence/models.py
zen_auth/server/persistence/session.py
zen_auth/server/usecases/__init__.py
zen_auth/server/usecases/app_service.py
zen_auth/server/usecases/rbac_checks.py
zen_auth/server/usecases/role_service.py
zen_auth/server/usecases/scope_service.py
zen_auth/server/usecases/user_service.py
zenauth_server-0.1.2.dist-info/licenses/LICENSE
zenauth_server-0.1.2.dist-info/METADATA
zenauth_server-0.1.2.dist-info/WHEEL
zenauth_server-0.1.2.dist-info/top_level.txt
zenauth_server-0.1.2.dist-info/RECORD
