Metadata-Version: 2.4
Name: ZenAuth-server
Version: 0.1.2
Summary: A user authentication and management library.
Author-email: Yusuke KITAGAWA <tonosama_kaeru@icloud.com>
License-Expression: MIT
Project-URL: Homepage, https://github.com/MeiRakuPapa/ZenAuth
Requires-Python: >=3.10
License-File: LICENSE
Requires-Dist: ZenAuth
Requires-Dist: zenhtml
Requires-Dist: pyyaml
Requires-Dist: passlib[bcrypt]
Requires-Dist: sqlalchemy
Requires-Dist: typing-extensions
Requires-Dist: fastapi
Requires-Dist: pydantic
Requires-Dist: pydantic-settings
Requires-Dist: requests
Requires-Dist: python-jose
Requires-Dist: python-dotenv
Requires-Dist: bcrypt<4.0.0
Requires-Dist: uvicorn
Requires-Dist: python-multipart
Provides-Extra: test
Requires-Dist: pytest; extra == "test"
Requires-Dist: pytest-cov; extra == "test"
Requires-Dist: pytest-mock; extra == "test"
Requires-Dist: httpx; extra == "test"
Provides-Extra: dev
Requires-Dist: autopep8; extra == "dev"
Requires-Dist: black; extra == "dev"
Requires-Dist: debugpy; extra == "dev"
Requires-Dist: flake8; extra == "dev"
Requires-Dist: mypy; extra == "dev"
Requires-Dist: mypy-extensions; extra == "dev"
Requires-Dist: ipython; extra == "dev"
Requires-Dist: build; extra == "dev"
Requires-Dist: twine; extra == "dev"
Requires-Dist: isort; extra == "dev"
Requires-Dist: pre-commit; extra == "dev"
Requires-Dist: faker; extra == "dev"
Requires-Dist: aiosqlite; extra == "dev"
Dynamic: license-file
